ms_requests_session/__init__.py
ms_requests_session/api.py
ms_requests_session-0.0.1.dist-info/LICENSE
ms_requests_session-0.0.1.dist-info/METADATA
ms_requests_session-0.0.1.dist-info/WHEEL
ms_requests_session-0.0.1.dist-info/RECORD
