Metadata-Version: 2.1
Name: ms-requests-session
Version: 0.0.1
Summary: Provides a requests session logged in to your Microsoft account
Home-page: https://github.com/zmarffy/ms_requests_session
License: MIT
Author: Zeke Marffy
Author-email: zmarffy@yahoo.com
Requires-Python: >=3.8.1,<4.0.0
Classifier: License :: OSI Approved :: MIT License
Classifier: Programming Language :: Python :: 3
Classifier: Programming Language :: Python :: 3.9
Classifier: Programming Language :: Python :: 3.10
Classifier: Programming Language :: Python :: 3.11
Classifier: Programming Language :: Python :: 3.12
Requires-Dist: beautifulsoup4 (>=4.12.3,<5.0.0)
Requires-Dist: poetry (>=1.8.3,<2.0.0)
Requires-Dist: requests (>=2.32.3,<3.0.0)
Project-URL: Repository, https://github.com/zmarffy/ms_requests_session
